april_vision/__init__.py
april_vision/_version.py
april_vision/detect_cameras.py
april_vision/frame_sources.py
april_vision/marker.py
april_vision/py.typed
april_vision/utils.py
april_vision/vision.py
april_vision/calibrations/Logitech B500.xml
april_vision/calibrations/Logitech C270.xml
april_vision/calibrations/Logitech C905.xml
april_vision/calibrations/Logitech C920.xml
april_vision/calibrations/__init__.py
april_vision/cli/__init__.py
april_vision/cli/annotate_image.py
april_vision/cli/annotate_video.py
april_vision/cli/calibrate.py
april_vision/cli/camera_benchmark.py
april_vision/cli/live.py
april_vision/cli/marker_benchmark.py
april_vision/cli/utils.py
april_vision/cli/vision_debug.py
april_vision/cli/marker_generator/__init__.py
april_vision/cli/marker_generator/marker_tile.py
april_vision/cli/marker_generator/utils.py
april_vision/cli/marker_generator/marker_modes/__init__.py
april_vision/cli/marker_generator/marker_modes/mode_cal.py
april_vision/cli/marker_generator/marker_modes/mode_image.py
april_vision/cli/marker_generator/marker_modes/mode_single.py
april_vision/cli/marker_generator/marker_modes/mode_tile.py
april_vision/cli/tools/__init__.py
april_vision/cli/tools/family_details.py
april_vision/cli/tools/list_cameras.py
april_vision/examples/__init__.py
april_vision/examples/camera.py
april_vision/examples/py.typed
april_vision/helpers/__init__.py
april_vision/helpers/markers.py
april_vision/helpers/py.typed
april_vision/helpers/sender.py
stubs/pyquaternion/__init__.pyi
stubs/pyquaternion/quaternion.pyi
tests/__init__.py
tests/test_marker_gen.py
tests/test_processor.py
tests/webots_generator/controllers/capture_robot/capture_robot.py
tests/webots_generator/controllers/capture_robot/keyboard_robot.py
tests/webots_generator/worlds/.webots_generator.wbproj
tests/webots_generator/worlds/CI.png
tests/webots_generator/worlds/webots_generator.wbt
april_vision-2.2.1.dist-info/LICENSE
april_vision-2.2.1.dist-info/METADATA
april_vision-2.2.1.dist-info/WHEEL
april_vision-2.2.1.dist-info/entry_points.txt
april_vision-2.2.1.dist-info/top_level.txt
april_vision-2.2.1.dist-info/RECORD
