Metadata-Version: 2.1
Name: april_vision
Version: 2.2.1
Summary: An AprilTags wrapper with camera discovery and axis conversion.
Author: Will Barber, Joshua Perriman
License: MIT License
Project-URL: Repository, https://github.com/WillB97/april_vision
Classifier: Topic :: Software Development :: Libraries :: Python Modules
Classifier: Topic :: Scientific/Engineering :: Image Recognition
Classifier: Programming Language :: Python :: 3
Classifier: Operating System :: OS Independent
Classifier: Development Status :: 5 - Production/Stable
Classifier: Typing :: Typed
Classifier: License :: OSI Approved :: MIT License
Requires-Python: >=3.8
License-File: LICENSE
Requires-Dist: pyapriltags<3.3.1,>=3.3.0.2
Requires-Dist: numpy<2,>=1.21
Requires-Dist: pyquaternion<1,>=0.9.9
Requires-Dist: winsdk<2,>=1.0.0b7; platform_system == "Windows"
Provides-Extra: cli
Requires-Dist: Pillow<10,>=9.4.0; extra == "cli"
Requires-Dist: tabulate<1,>=0.9.0; extra == "cli"
Requires-Dist: font-roboto>=0.0.1; extra == "cli"
Provides-Extra: dev
Requires-Dist: poethepoet<1,>=0.0.1; extra == "dev"
Requires-Dist: ruff<0.4,>=0.3.0; extra == "dev"
Requires-Dist: mypy==1.9.0; extra == "dev"
Requires-Dist: build; extra == "dev"
Requires-Dist: types-Pillow; extra == "dev"
Requires-Dist: types-tabulate; extra == "dev"
Requires-Dist: pytest; extra == "dev"
Requires-Dist: pytest-cov; extra == "dev"
Provides-Extra: opencv
Requires-Dist: opencv-python-headless<4.9,>=4; extra == "opencv"
